LICENSE
README.md
setup.cfg
setup.py
resultbox/__init__.py
resultbox/adapters.py
resultbox/box.py
resultbox/constants.py
resultbox/dct.py
resultbox/namespace.py
resultbox/persist.py
resultbox/plot.py
resultbox/settings.py
resultbox/table.py
resultbox/utils.py
resultbox/variable.py
resultbox.egg-info/PKG-INFO
resultbox.egg-info/SOURCES.txt
resultbox.egg-info/dependency_links.txt
resultbox.egg-info/requires.txt
resultbox.egg-info/top_level.txt
test/test_box.py
test/test_dct.py
test/test_persist.py
test/test_table.py
test/test_utils.py
test/test_variable.py