Metadata-Version: 2.1
Name: resultbox
Version: 0.2.0
Summary: Easily manage, tabulate, plot, and store analysis results.
Home-page: https://github.com/pythoro/resultbox.git
Download-URL: https://github.com/pythoro/resultbox/archive/v0.0.5.zip
Author: Reuben Rusk
Author-email: pythoro@mindquip.com
Keywords: RESULTS
Classifier: Programming Language :: Python :: 3.6
Classifier: Programming Language :: Python :: 3.7
Classifier: Development Status :: 3 - Alpha
Classifier: License :: OSI Approved :: MIT License
Classifier: Operating System :: OS Independent
Classifier: Natural Language :: English
Classifier: Topic :: Software Development :: Libraries :: Python Modules
License-File: LICENSE
